gxconfig/__init__.py
gxconfig/utils.py
gxconfig-0.0.2.dist-info/METADATA
gxconfig-0.0.2.dist-info/WHEEL
gxconfig-0.0.2.dist-info/top_level.txt
gxconfig-0.0.2.dist-info/RECORD
