Metadata-Version: 2.1
Name: gxconfig
Version: 0.0.2
Summary: A Global config tools created by gawainx
Home-page: UNKNOWN
Author: gawainx
Author-email: liangyi@bupt.edu.cn
License: UNKNOWN
Platform: UNKNOWN
Classifier: Programming Language :: Python :: 3.7
Classifier: License :: OSI Approved :: MIT License
Classifier: Operating System :: OS Independent
Requires-Dist: toml
